{
	"parent": "item/handheld",
	"textures": {
		"layer0": "projectdawn:items/arcane_sword_full"
	},
	"gui_light": "front",
	"overrides": [
		{
			"predicate": {
				"drained": 1
			},
			"model": "projectdawn:item/arcane_sword_drained"
		}
	],
	"display": {
		"thirdperson_righthand": {
			"rotation": [-10, -90, 45],
			"translation": [0, 12, -1.2],
			"scale": [1.725, 1.725, 0.875]
		},
		"thirdperson_lefthand": {
			"rotation": [-10, 90, -45],
			"translation": [0, 12, -1.2],
			"scale": [1.725, 1.725, 0.875]
		},
		"firstperson_righthand": {
			"rotation": [-180, -90, -150],
			"translation": [1, 10.25, 3],
			"scale": [1.5, 1.5, 0.75]
		},
		"firstperson_lefthand": {
			"rotation": [-180, 90, 150],
			"translation": [1, 10.25, 3],
			"scale": [1.5, 1.5, 0.75]
		},
		"ground": {
			"translation": [2.75, 4.25, 0],
			"scale": [1, 1, 0.5]
		},
		"gui": {
			"translation": [3.15, 3.15, 0],
			"scale": [1.39, 1.39, 1.375]
		},
		"fixed": {
			"rotation": [-180, 0, -180],
			"translation": [-3.25, 3.25, -0.25],
			"scale": [1.55, 1.55, 0.55]
		}
	}
}